microcosm_elasticsearch/__init__.py
microcosm_elasticsearch/assertions.py
microcosm_elasticsearch/decorators.py
microcosm_elasticsearch/errors.py
microcosm_elasticsearch/factories.py
microcosm_elasticsearch/fields.py
microcosm_elasticsearch/main.py
microcosm_elasticsearch/mapping.py
microcosm_elasticsearch/models.py
microcosm_elasticsearch/registry.py
microcosm_elasticsearch/searching.py
microcosm_elasticsearch/store.py
microcosm_elasticsearch/index_status/__init__.py
microcosm_elasticsearch/index_status/convention.py
microcosm_elasticsearch/index_status/models.py
microcosm_elasticsearch/index_status/resources.py
microcosm_elasticsearch/index_status/store.py
microcosm_elasticsearch-8.0.0.dist-info/LICENSE
microcosm_elasticsearch-8.0.0.dist-info/METADATA
microcosm_elasticsearch-8.0.0.dist-info/WHEEL
microcosm_elasticsearch-8.0.0.dist-info/entry_points.txt
microcosm_elasticsearch-8.0.0.dist-info/top_level.txt
microcosm_elasticsearch-8.0.0.dist-info/RECORD
